spyral/__init__.py
spyral/cli.py
spyral_cli-1.1.2.dist-info/METADATA
spyral_cli-1.1.2.dist-info/WHEEL
spyral_cli-1.1.2.dist-info/entry_points.txt
spyral_cli-1.1.2.dist-info/RECORD
