Metadata-Version: 2.1
Name: spyral-cli
Version: 1.1.2
Summary: 
License: MIT
Author: Paul Gessinger
Author-email: hello@paulgessinger.com
Requires-Python: >=3.9
Classifier: License :: OSI Approved :: MIT License
Classifier: Programming Language :: Python :: 3
Classifier: Programming Language :: Python :: 3.9
Classifier: Programming Language :: Python :: 3.10
Classifier: Programming Language :: Python :: 3.11
Requires-Dist: backports-strenum (>=1.2.4,<2.0.0)
Requires-Dist: numpy (>=1.25.0,<2.0.0)
Requires-Dist: pandas (>=2.0.3,<3.0.0)
Requires-Dist: plotext (>=5.2.8,<6.0.0)
Requires-Dist: psutil (>=5.9.5,<6.0.0)
Requires-Dist: rich (>=13.4.2,<14.0.0)
Requires-Dist: typer (>=0.9.0,<0.10.0)
